MANIFEST.in
README.rst
setup.py
twisted/plugins/dropin.cache
twisted/plugins/txsyncml_plugin.py
txsyncml/__init__.py
txsyncml/codecs.py
txsyncml/commands.py
txsyncml/constants.py
txsyncml/parser.py
txsyncml/resource.py
txsyncml/service.py
txsyncml/syncml.py
txsyncml/wbxml.py
txsyncml.egg-info/PKG-INFO
txsyncml.egg-info/SOURCES.txt
txsyncml.egg-info/dependency_links.txt
txsyncml.egg-info/requires.txt
txsyncml.egg-info/top_level.txt
txsyncml/tests/__init__.py
txsyncml/tests/helpers.py
txsyncml/tests/test_base.py
txsyncml/tests/test_codecs.py
txsyncml/tests/test_commands.py
txsyncml/tests/test_parser.py
txsyncml/tests/test_resource.py
txsyncml/tests/test_wbxml.py
txsyncml/tests/fixtures/__init__.py