Metadata-Version: 1.1
Name: txsyncml
Version: 0.0.1
Summary: Twisted based SyncML 1.1 server.
Home-page: http://github.com/smn/txsyncml
Author: Simon de Haan
Author-email: simon@praekeltfoundation.org
License: BSD
Platform: UNKNOWN
Classifier: Development Status :: 3 - Alpha
Classifier: Intended Audience :: Developers
Classifier: License :: OSI Approved :: BSD License
Classifier: Operating System :: POSIX
Classifier: Programming Language :: Python
Classifier: Topic :: Software Development :: Libraries :: Python Modules
Classifier: Topic :: System :: Networking
Classifier: Framework :: Twisted
